pygame/SDL.dll
pygame/SDL_image.dll
pygame/SDL_mixer.dll
pygame/SDL_ttf.dll
pygame/__init__.py
pygame/_error.py
pygame/_jpg.py
pygame/_jpg_c.pyd
pygame/_png.py
pygame/_png_c.pyd
pygame/_sdl.py
pygame/_sdl_c.pyd
pygame/_sdl_keys.py
pygame/_sdl_keys_c.pyd
pygame/base.py
pygame/bufferproxy.py
pygame/color.py
pygame/colordict.py
pygame/compat.py
pygame/constants.py
pygame/cursors.py
pygame/display.py
pygame/draw.py
pygame/event.py
pygame/font.py
pygame/freesansbold.ttf
pygame/image.py
pygame/joystick.py
pygame/key.py
pygame/libfreetype-6.dll
pygame/libgcc_s_sjlj-1.dll
pygame/libjpeg-8.dll
pygame/libmpg123-0.dll
pygame/libogg-0.dll
pygame/libpng16-16.dll
pygame/libstdc++-6.dll
pygame/libtiff-5.dll
pygame/libvorbis-0.dll
pygame/libvorbisfile-3.dll
pygame/libwebp-5.dll
pygame/locals.py
pygame/macosx.py
pygame/mask.py
pygame/math.py
pygame/mixer.py
pygame/mixer_music.py
pygame/mouse.py
pygame/pkgdata.py
pygame/portmidi.dll
pygame/pygame_icon.bmp
pygame/pygame_icon.icns
pygame/pygame_icon.svg
pygame/pygame_icon.tiff
pygame/rect.py
pygame/rwobject.py
pygame/sprite.py
pygame/surface.py
pygame/surflock.py
pygame/sysfont.py
pygame/threads.py
pygame/time.py
pygame/transform.py
pygame/version.py
pygame/zlib1.dll
pygame_cffi-0.2.1.dist-info/DESCRIPTION.rst
pygame_cffi-0.2.1.dist-info/METADATA
pygame_cffi-0.2.1.dist-info/RECORD
pygame_cffi-0.2.1.dist-info/WHEEL
pygame_cffi-0.2.1.dist-info/metadata.json
pygame_cffi-0.2.1.dist-info/top_level.txt
