Metadata-Version: 2.0
Name: pygame-cffi
Version: 0.2.1
Summary: A cffi-based SDL wrapper that copies the pygame API.
Home-page: http://github.com/CTPUG/pygame_cffi
Author: UNKNOWN
Author-email: UNKNOWN
License: LGPL-2.1+
Platform: UNKNOWN
Classifier: Development Status :: 4 - Beta
Classifier: Intended Audience :: Developers
Classifier: License :: OSI Approved :: GNU Lesser General Public License v2 or later (LGPLv2+)
Classifier: Operating System :: POSIX
Classifier: Programming Language :: Python
Classifier: Programming Language :: Python :: 2.7
Classifier: Programming Language :: Python :: 3
Classifier: Topic :: Software Development :: Libraries :: Python Modules
Requires-Dist: cffi (>=1.3.0)
